{
    "resources": [
        {
            "asset_id": "d22b339f3ab011b14235c7eb6ddc37fb",
            "public_id": "Screenshot_5_xpxyzj",
            "format": "png",
            "version": 1660899530,
            "resource_type": "image",
            "type": "upload",
            "created_at": "2022-08-19T08:58:50Z",
            "bytes": 288785,
            "width": 1920,
            "height": 1080,
            "folder": "",
            "access_mode": "public",
            "url": "http://res.cloudinary.com/gajapathi/image/upload/v1660899530/Screenshot_5_xpxyzj.png",
            "secure_url": "https://res.cloudinary.com/gajapathi/image/upload/v1660899530/Screenshot_5_xpxyzj.png"
        },
        {
            "asset_id": "eddf7f96d0d05d305fbe1d6df37f351b",
            "public_id": "Screenshot_6_ojklce",
            "format": "png",
            "version": 1660899530,
            "resource_type": "image",
            "type": "upload",
            "created_at": "2022-08-19T08:58:50Z",
            "bytes": 249985,
            "width": 1920,
            "height": 1080,
            "folder": "",
            "access_mode": "public",
            "url": "http://res.cloudinary.com/gajapathi/image/upload/v1660899530/Screenshot_6_ojklce.png",
            "secure_url": "https://res.cloudinary.com/gajapathi/image/upload/v1660899530/Screenshot_6_ojklce.png"
        },
        {
            "asset_id": "9fcee485e16a0f49de3c8a1d57f2b51d",
            "public_id": "Screenshot_13_rb8whc",
            "format": "png",
            "version": 1660899530,
            "resource_type": "image",
            "type": "upload",
            "created_at": "2022-08-19T08:58:50Z",
            "bytes": 271791,
            "width": 1920,
            "height": 1080,
            "folder": "",
            "access_mode": "public",
            "url": "http://res.cloudinary.com/gajapathi/image/upload/v1660899530/Screenshot_13_rb8whc.png",
            "secure_url": "https://res.cloudinary.com/gajapathi/image/upload/v1660899530/Screenshot_13_rb8whc.png"
        },
        {
            "asset_id": "8ec0499de5b0d75a6c4950cd63b55d3c",
            "public_id": "Screenshot_10_kkmo5y",
            "format": "png",
            "version": 1660899530,
            "resource_type": "image",
            "type": "upload",
            "created_at": "2022-08-19T08:58:50Z",
            "bytes": 263322,
            "width": 1920,
            "height": 1080,
            "folder": "",
            "access_mode": "public",
            "url": "http://res.cloudinary.com/gajapathi/image/upload/v1660899530/Screenshot_10_kkmo5y.png",
            "secure_url": "https://res.cloudinary.com/gajapathi/image/upload/v1660899530/Screenshot_10_kkmo5y.png"
        },
        {
            "asset_id": "eae451d2eaa8c5b1f69804eddce0a77d",
            "public_id": "Screenshot_4_qikwnn",
            "format": "png",
            "version": 1660899530,
            "resource_type": "image",
            "type": "upload",
            "created_at": "2022-08-19T08:58:50Z",
            "bytes": 291438,
            "width": 1920,
            "height": 1080,
            "folder": "",
            "access_mode": "public",
            "url": "http://res.cloudinary.com/gajapathi/image/upload/v1660899530/Screenshot_4_qikwnn.png",
            "secure_url": "https://res.cloudinary.com/gajapathi/image/upload/v1660899530/Screenshot_4_qikwnn.png"
        },
        {
            "asset_id": "3bc009e4fdbf5fc1bb83a421c2e0095b",
            "public_id": "kp3zv4o2msizbvscmva0",
            "format": "png",
            "version": 1660844659,
            "resource_type": "image",
            "type": "upload",
            "created_at": "2022-08-18T17:44:19Z",
            "bytes": 92886,
            "width": 1590,
            "height": 869,
            "folder": "",
            "access_mode": "public",
            "url": "http://res.cloudinary.com/gajapathi/image/upload/v1660844659/kp3zv4o2msizbvscmva0.png",
            "secure_url": "https://res.cloudinary.com/gajapathi/image/upload/v1660844659/kp3zv4o2msizbvscmva0.png"
        },
        {
            "asset_id": "12095f66ea918e477d0d71d083651dae",
            "public_id": "l6svaax8dnbhfdsd6dkk",
            "format": "png",
            "version": 1660843755,
            "resource_type": "image",
            "type": "upload",
            "created_at": "2022-08-18T17:29:15Z",
            "bytes": 92886,
            "width": 1590,
            "height": 869,
            "folder": "",
            "access_mode": "public",
            "url": "http://res.cloudinary.com/gajapathi/image/upload/v1660843755/l6svaax8dnbhfdsd6dkk.png",
            "secure_url": "https://res.cloudinary.com/gajapathi/image/upload/v1660843755/l6svaax8dnbhfdsd6dkk.png"
        },
        {
            "asset_id": "38788c81ff41d4d892a52f8453ea1ac6",
            "public_id": "h5mng6ho8rg2djyrqxug",
            "format": "png",
            "version": 1660843548,
            "resource_type": "image",
            "type": "upload",
            "created_at": "2022-08-18T17:25:48Z",
            "bytes": 92886,
            "width": 1590,
            "height": 869,
            "folder": "",
            "access_mode": "public",
            "url": "http://res.cloudinary.com/gajapathi/image/upload/v1660843548/h5mng6ho8rg2djyrqxug.png",
            "secure_url": "https://res.cloudinary.com/gajapathi/image/upload/v1660843548/h5mng6ho8rg2djyrqxug.png"
        },
        {
            "asset_id": "501e09f368f2a07881bc1dcaff5c4328",
            "public_id": "y6to1zetgh6o36yxwmoa",
            "format": "png",
            "version": 1660817461,
            "resource_type": "image",
            "type": "upload",
            "created_at": "2022-08-18T10:11:01Z",
            "bytes": 92886,
            "width": 1590,
            "height": 869,
            "folder": "",
            "access_mode": "public",
            "url": "http://res.cloudinary.com/gajapathi/image/upload/v1660817461/y6to1zetgh6o36yxwmoa.png",
            "secure_url": "https://res.cloudinary.com/gajapathi/image/upload/v1660817461/y6to1zetgh6o36yxwmoa.png"
        },
        {
            "asset_id": "051d412a5f156efaed372b4aba118fa6",
            "public_id": "dyx0nj8dt3dnclviwhoc",
            "format": "png",
            "version": 1660817461,
            "resource_type": "image",
            "type": "upload",
            "created_at": "2022-08-18T10:11:01Z",
            "bytes": 92886,
            "width": 1590,
            "height": 869,
            "folder": "",
            "access_mode": "public",
            "url": "http://res.cloudinary.com/gajapathi/image/upload/v1660817461/dyx0nj8dt3dnclviwhoc.png",
            "secure_url": "https://res.cloudinary.com/gajapathi/image/upload/v1660817461/dyx0nj8dt3dnclviwhoc.png"
        }
    ],
    "next_cursor": "e9ae77c3e66d74aca63ab708551a4d9fd39f42f4a9b12c3f291f1ea26df2e440"
}